dataloom/__init__.py
dataloom/keys.py
dataloom/columns/__init__.py
dataloom/conn/__init__.py
dataloom/constants/__init__.py
dataloom/decorators/__init__.py
dataloom/exceptions/__init__.py
dataloom/loom/__init__.py
dataloom/loom/delete.py
dataloom/loom/insert.py
dataloom/loom/inspect.py
dataloom/loom/interfaces.py
dataloom/loom/math.py
dataloom/loom/qb.py
dataloom/loom/query.py
dataloom/loom/sql.py
dataloom/loom/subqueries.py
dataloom/loom/update.py
dataloom/model/__init__.py
dataloom/statements/__init__.py
dataloom/statements/statements.py
dataloom/tests/mysql/test_aggregation_mysql.py
dataloom/tests/mysql/test_alter_tables_mysql.py
dataloom/tests/mysql/test_connection_options_mysql.py
dataloom/tests/mysql/test_connection_uri_mysql.py
dataloom/tests/mysql/test_create_tables_mysql.py
dataloom/tests/mysql/test_delete_mysql.py
dataloom/tests/mysql/test_eager_loading_mysql.py
dataloom/tests/mysql/test_experimental_decorators_mysql.py
dataloom/tests/mysql/test_insert_mysql.py
dataloom/tests/mysql/test_inspect_table_mysql.py
dataloom/tests/mysql/test_operators_mysql.py
dataloom/tests/mysql/test_qb_mysql.py
dataloom/tests/mysql/test_query_msql.py
dataloom/tests/mysql/test_update_mysql.py
dataloom/tests/mysql/test_utils_fns_mysql.py
dataloom/tests/postgres/test_aggregation_pg.py
dataloom/tests/postgres/test_alter_tables_pg.py
dataloom/tests/postgres/test_connection_options_pg.py
dataloom/tests/postgres/test_connection_uri_pg.py
dataloom/tests/postgres/test_create_table_pg.py
dataloom/tests/postgres/test_delete_pg.py
dataloom/tests/postgres/test_eager_loading_pg.py
dataloom/tests/postgres/test_experimental_decorators_pg.py
dataloom/tests/postgres/test_insert_pg.py
dataloom/tests/postgres/test_inspecting_table_pg.py
dataloom/tests/postgres/test_operators_pg.py
dataloom/tests/postgres/test_qb_pg.py
dataloom/tests/postgres/test_query_pg.py
dataloom/tests/postgres/test_update_pg.py
dataloom/tests/postgres/test_utils_fns_pg.py
dataloom/tests/sqlite3/test_aggregation_sqlite.py
dataloom-2.4.2.dist-info/LICENSE
dataloom-2.4.2.dist-info/METADATA
dataloom-2.4.2.dist-info/WHEEL
dataloom-2.4.2.dist-info/top_level.txt
dataloom-2.4.2.dist-info/RECORD
