Metadata-Version: 2.1
Name: dataloom
Version: 2.4.2
Summary: dataloom stands as a bespoke Object-Relational Mapping (ORM) solution meticulously crafted to empower Python developers in efficiently managing diverse databases. Unlike conventional ORMs, Dataloom has been built from the ground up, providing native support for SQLite3, PostgreSQL, and MySQL. Navigate effortlessly between database engines while enjoying a tailored and performant ORM experience.
Author-email: Crispen Gari <crispengari@gmail.com>
License: MIT License
Project-URL: homepage, https://github.com/CrispenGari/dataloom
Project-URL: repository, https://github.com/CrispenGari/dataloom
Project-URL: documentation, https://github.com/CrispenGari/dataloom/blob/main/README.md
Project-URL: changelog, https://github.com/CrispenGari/dataloom/blob/main/CHANGELOG.md
Project-URL: issues, https://github.com/CrispenGari/dataloom/issues
Keywords: ORM,database,data management,SQLAlchemy
Classifier: Development Status :: 5 - Production/Stable
Classifier: Development Status :: 6 - Mature
Classifier: Intended Audience :: Developers
Classifier: Programming Language :: Python :: 3.12
Classifier: Operating System :: Unix
Classifier: Operating System :: MacOS :: MacOS X
Classifier: Operating System :: Microsoft :: Windows
Classifier: Operating System :: Unix
Classifier: Operating System :: MacOS :: MacOS X
Classifier: Operating System :: Microsoft :: Windows
Classifier: Natural Language :: English
Requires-Python: >=3.12
License-File: LICENSE
Requires-Dist: mysql-connector-python ==8.3.0
Requires-Dist: psycopg2 ==2.9.9
Requires-Dist: typing-extensions ==4.9.0
